fluidsim_core/__init__.py
fluidsim_core/extend_simul.py
fluidsim_core/hexa_files.py
fluidsim_core/info.py
fluidsim_core/ipy_load.py
fluidsim_core/loader.py
fluidsim_core/magic.py
fluidsim_core/params.py
fluidsim_core/paths.py
fluidsim_core/solver.py
fluidsim_core/output/__init__.py
fluidsim_core/output/base.py
fluidsim_core/output/dataframe_from_paths.py
fluidsim_core/output/movies.py
fluidsim_core/output/phys_fields.py
fluidsim_core/output/phys_fields_snek5000.py
fluidsim_core/output/remaining_clock_time.py
fluidsim_core/scripts/__init__.py
fluidsim_core/scripts/restart.py
fluidsim_core/tests/__init__.py
fluidsim_core/tests/conftest.py
fluidsim_core/tests/solver.py
fluidsim_core/tests/test_hexa_files.py
fluidsim_core/tests/test_loader.py
fluidsim_core/tests/test_output_movies.py
fluidsim_core/tests/test_solver.py
fluidsim_core/tests/test_solver_with_output.py
fluidsim_core-0.9.0.dist-info/entry_points.txt
fluidsim_core-0.9.0.dist-info/licenses/LICENSE.txt
fluidsim_core-0.9.0.dist-info/WHEEL
fluidsim_core-0.9.0.dist-info/METADATA
fluidsim_core-0.9.0.dist-info/RECORD
