Metadata-Version: 2.4
Name: fluidsim-core
Version: 0.9.0
Summary: Pure-Python core library for FluidSim framework
Author-email: "pierre.augier" <pierre.augier@univ-grenoble-alpes.fr>
Requires-Python: >=3.11
License-Expression: CECILL-2.1
License-File: LICENSE.txt
Requires-Dist: fluiddyn
